Metadata-Version: 1.2
Name: pydict-surf
Version: 0.7.28
Summary: Performs a walk over all fields of json and python dictionary. Works almost same as os.walk
Home-page: UNKNOWN
Author: Soroush Zargar, Hemen Zandi
Author-email: Soroushzargar@gmail.com, Hemen.Zandi@gmail.com
License: UNKNOWN
Platform: UNKNOWN
Classifier: Programming Language :: Python :: 3
Classifier: License :: OSI Approved :: MIT License
Classifier: Operating System :: OS Independent
Requires-Python: >=3.7
